adafruit_circuitpython_seesaw-1.18.0.dist-info/licenses/LICENSE
adafruit_seesaw/__init__.py
adafruit_seesaw/analoginput.py
adafruit_seesaw/attiny8x7.py
adafruit_seesaw/attinyx16.py
adafruit_seesaw/crickit.py
adafruit_seesaw/digitalio.py
adafruit_seesaw/keypad.py
adafruit_seesaw/neopixel.py
adafruit_seesaw/pwmout.py
adafruit_seesaw/robohat.py
adafruit_seesaw/rotaryio.py
adafruit_seesaw/samd09.py
adafruit_seesaw/seesaw.py
adafruit_seesaw/tftshield18.py
adafruit_circuitpython_seesaw-1.18.0.dist-info/METADATA
adafruit_circuitpython_seesaw-1.18.0.dist-info/WHEEL
adafruit_circuitpython_seesaw-1.18.0.dist-info/top_level.txt
adafruit_circuitpython_seesaw-1.18.0.dist-info/RECORD
